{
    "object_coords": "(19473.37818388666, 24166.31881202761, 0.3958869276496625)",
    "object_type": "ObjectType.PERSON",
    "drone_rel_coords": "(-18, -1, 44)",
    "seed": "371751210",
    "forest_live_trees_density": "0.21634754184943283",
    "forest_dead_trees_density": "0.024038615761048095",
    "forest_stones": "0.08078576727046148",
    "forest_cliffs": "0",
    "sun_y": "-86.5812355529565",
    "sun_z": "323.80367789066355",
    "regenerate_forest": "True",
    "set_object": "True",
    "cansee_restarts": "0",
    "object_id": "Actor_UAID_08BFB8191750FD4202_1997655724",
    "passed_object_name": "a person"
}