{
    "object_coords": "(32816.33221155024, 29500.469567233733, 0.20724690472144336)",
    "object_type": "ObjectType.CAMPSITE",
    "drone_rel_coords": "(30, -30, 77)",
    "seed": "994495170",
    "forest_live_trees_density": "0.01694447453156799",
    "forest_dead_trees_density": "0.0018827193923964432",
    "forest_stones": "0.04999079975431963",
    "forest_cliffs": "0",
    "sun_y": "-12.588418102411907",
    "sun_z": "193.91812847275193",
    "regenerate_forest": "True",
    "set_object": "True",
    "cansee_restarts": "0",
    "object_id": "StaticMeshActor_UAID_08BFB81917501C3F02_1703388951",
    "passed_object_name": "a campsite"
}